subgen/__init__.py
subgen/subgen/__init__.py
subgen/subgen/cli.py
subgen-0.0.1.dist-info/LICENSE
subgen-0.0.1.dist-info/METADATA
subgen-0.0.1.dist-info/WHEEL
subgen-0.0.1.dist-info/entry_points.txt
subgen-0.0.1.dist-info/top_level.txt
subgen-0.0.1.dist-info/RECORD
