Metadata-Version: 2.1
Name: subgen
Version: 0.0.1
Summary: Subdomain wordlist generator
Home-page: https://github.com/shriyanss/subdomain_wordlist_gen
Author: Shriyans Sudhi
License: UNKNOWN
Platform: UNKNOWN
Classifier: Programming Language :: Python :: 3
Classifier: License :: OSI Approved :: MIT License
Classifier: Operating System :: POSIX :: Linux
Classifier: Operating System :: MacOS :: MacOS X
Classifier: Operating System :: Unix
Requires-Python: >=3.6
License-File: LICENSE
Requires-Dist: pyfiglet
Requires-Dist: tldextract
